doc_tour-0.1.4.data/scripts/doctour
doctour/__init__.py
doctour/_nbdev.py
doctour/config.py
doctour/doctour
doctour/run.py
doctour/app/__init__.py
doctour/app/dbs/__init__.py
doctour/app/models/__init__.py
doctour/app/models/lib.py
doctour/app/static/appbuilder/css/ab.css
doctour/app/static/appbuilder/css/bootstrap.min.css
doctour/app/static/appbuilder/css/font-awesome.min.css
doctour/app/static/appbuilder/css/flags/flags16.css
doctour/app/static/appbuilder/css/themes/amelia.css
doctour/app/static/appbuilder/css/themes/cerulean.css
doctour/app/static/appbuilder/css/themes/cosmo.css
doctour/app/static/appbuilder/css/themes/cyborg.css
doctour/app/static/appbuilder/css/themes/darkly.css
doctour/app/static/appbuilder/css/themes/flatly.css
doctour/app/static/appbuilder/css/themes/journal.css
doctour/app/static/appbuilder/css/themes/lumen.css
doctour/app/static/appbuilder/css/themes/paper.css
doctour/app/static/appbuilder/css/themes/readable.css
doctour/app/static/appbuilder/css/themes/sandstone.css
doctour/app/static/appbuilder/css/themes/simplex.css
doctour/app/static/appbuilder/css/themes/slate.css
doctour/app/static/appbuilder/css/themes/solar.css
doctour/app/static/appbuilder/css/themes/spacelab.css
doctour/app/static/appbuilder/css/themes/superhero.css
doctour/app/static/appbuilder/css/themes/united.css
doctour/app/static/appbuilder/css/themes/yeti.css
doctour/app/static/appbuilder/datepicker/bootstrap-datepicker.css
doctour/app/static/appbuilder/datepicker/bootstrap-datepicker.js
doctour/app/static/appbuilder/fonts/FontAwesome.otf
doctour/app/static/appbuilder/fonts/fontawesome-webfont.eot
doctour/app/static/appbuilder/fonts/fontawesome-webfont.svg
doctour/app/static/appbuilder/fonts/fontawesome-webfont.ttf
doctour/app/static/appbuilder/fonts/fontawesome-webfont.woff
doctour/app/static/appbuilder/fonts/fontawesome-webfont.woff2
doctour/app/static/appbuilder/fonts/glyphicons-halflings-regular.eot
doctour/app/static/appbuilder/fonts/glyphicons-halflings-regular.svg
doc_tour-0.1.4.dist-info/LICENSE
doc_tour-0.1.4.dist-info/METADATA
doc_tour-0.1.4.dist-info/WHEEL
doc_tour-0.1.4.dist-info/top_level.txt
doc_tour-0.1.4.dist-info/RECORD
