Metadata-Version: 2.1
Name: doc-tour
Version: 0.1.4
Summary: A web UI for detailed python coding
Home-page: UNKNOWN
Author: raynardj
Author-email: raynard@rasenn.com
License: UNKNOWN
Platform: UNKNOWN
Classifier: Programming Language :: Python :: 3
Classifier: Operating System :: OS Independent
Requires-Python: >=3.6
Requires-Dist: flask
Requires-Dist: flask-appbuilder (==2.2.2)
